kk_ontology_module/__init__.py
kk_ontology_module/datamanip.py
kk_ontology_module/load_data.py
kk_ontology_module/load_onto.py
kk_ontology_module/main.py
kk_ontology_module/map_data.py
kk_ontology_module/reason.py
kk_ontology_module/extras/BreastCancerOntology.owl
kk_ontology_module/extras/CancerOntology.owl
kk_ontology_module/extras/m2dummyB_small.csv
kk_ontology_module/extras/m2dummy_med.csv
tests/__init__.py
tests/test_gliocova.py
tests/test_load.py
tests/test_load_no_col.py
tests/test_load_onto.py
tests/test_map.py
tests/test_reason.py
tests/test_to_pandas.py
kk_ontology_module-1.0.22.dist-info/LICENSE.txt
kk_ontology_module-1.0.22.dist-info/METADATA
kk_ontology_module-1.0.22.dist-info/WHEEL
kk_ontology_module-1.0.22.dist-info/top_level.txt
kk_ontology_module-1.0.22.dist-info/RECORD
